Workbook

Sheet Portada
B2: Evergreen Love L.L.C.
B3: Libro de Contabilidad e Impuestos
B4: Guaynabo, Puerto Rico • Preparado para uso interno del negocio
B6: Cómo usar este libro
B7: 1. Registra cada venta en la pestaña 'Ingresos' y cada gasto en la pestaña 'Gastos'. Esas dos pestañas son las únicas donde debes escribir información nueva.
B8: 2. Las pestañas 'Resumen Mensual', 'IVU Mensual' y 'Contribución sobre Ingresos' se calculan solas con fórmulas — no escribas datos ahí, solo revisa los resultados.
B9: 3. Cambia el año en la celda amarilla de cada pestaña de resumen si vas a trabajar un año distinto (por ejemplo, 2025 vs. 2026).
B10: 4. Lee la pestaña 'Guía y Fechas' para las fechas límite de las planillas de IVU y de Contribución sobre Ingresos.
B12: Código de colores
C13: Amarillo = celda que debes llenar o revisar (ej. el año)
C14: Blanco con borde = celdas de fórmula, no editar
B17: Aviso importante: Esta herramienta es una ayuda de organización contable. Evergreen Love L.L.C. debe confirmar con un(a) Contador(a) Público(a) Autorizado(a) (CPA) en Puerto Rico la clasificación contributiva correcta de la LLC (corporación, sociedad o entidad no tomada en cuenta) y la preparación final de las planillas ante el Departamento de Hacienda. Este archivo no sustituye asesoría profesional de contabilidad o legal.
B19: Sincronización con Shopify (www.evergreenlovepr.com)
B20: Cada mes, antes del día 20 (fecha límite de IVU), se revisan automáticamente las órdenes nuevas de la tienda Shopify y se agregan a la pestaña 'Ingresos' con Fuente = 'Shopify' y su número de orden en la columna 'ID de Orden'. Las ventas que no pasan por la tienda (efectivo, ATH Móvil, ferias, etc.) las sigues anotando tú manualmente con Fuente = 'Manual'. Así el archivo en tu carpeta siempre está listo para revisar y usar en tus planillas de IVU y de Contribución sobre Ingresos.

Sheet Ingresos
A1: Fecha | B1: Cliente | C1: Descripción | D1: Categoría de Producto | E1: Método de Pago | F1: ¿Sujeto a IVU? | G1: Monto de Venta (sin IVU) | H1: IVU Cobrado | I1: Total Cobrado | J1: Fuente | K1: ID de Orden (Shopify)
I2: =IF(G2="","",G2+H2) | J2: Manual
I3: =IF(G3="","",G3+H3)
I4: =IF(G4="","",G4+H4)
I5: =IF(G5="","",G5+H5)
I6: =IF(G6="","",G6+H6)
I7: =IF(G7="","",G7+H7)
I8: =IF(G8="","",G8+H8)
I9: =IF(G9="","",G9+H9)
I10: =IF(G10="","",G10+H10)
I11: =IF(G11="","",G11+H11)
I12: =IF(G12="","",G12+H12)
I13: =IF(G13="","",G13+H13)
I14: =IF(G14="","",G14+H14)
... I299: =IF(G299="","",G299+H299)
B300: ↑ Fila 2 es un ejemplo (texto azul). Bórrala o sobrescríbela y continúa agregando tus ventas reales debajo.

Sheet Gastos
A1: Fecha | B1: Proveedor/Comercio | C1: Descripción | D1: Categoría de Gasto | E1: Método de Pago | F1: Monto | G1: ¿Deducible? | H1: IVU Pagado (crédito potencial)
B300: ↑ Fila 2 es un ejemplo (texto azul). Bórrala o sobrescríbela y continúa agregando tus gastos reales debajo.

Sheet Resumen Mensual
A1: Resumen Mensual de Ingresos y Gastos
A2: Año: | B2: 2026
A4: Mes | B4: Ingresos Totales | C4: Gastos Totales | D4: Utilidad Neta | F4: Inicio | G4: Fin
A5: Enero | B5: =SUMIFS(Ingresos!$G:$G,Ingresos!$A:$A,">="&F5,Ingresos!$A:$A,"<="&G5) -> 0 | C5: =SUMIFS(Gastos!$F:$F,Gastos!$A:$A,">="&F5,Gastos!$A:$A,"<="&G5) -> 0 | D5: =B5-C5 -> 0 | F5: =DATE($B$2,1,1) -> 46023 | G5: =EOMONTH(F5,0) -> 46053
A6: Febrero | B6: =SUMIFS(Ingresos!$G:$G,Ingresos!$A:$A,">="&F6,Ingresos!$A:$A,"<="&G6) -> 0 | C6: =SUMIFS(Gastos!$F:$F,Gastos!$A:$A,">="&F6,Gastos!$A:$A,"<="&G6) -> 0 | D6: =B6-C6 -> 0 | F6: =DATE($B$2,2,1) -> 46054 | G6: =EOMONTH(F6,0) -> 46081
A7: Marzo | B7: =SUMIFS(Ingresos!$G:$G,Ingresos!$A:$A,">="&F7,Ingresos!$A:$A,"<="&G7) -> 0 | C7: =SUMIFS(Gastos!$F:$F,Gastos!$A:$A,">="&F7,Gastos!$A:$A,"<="&G7) -> 0 | D7: =B7-C7 -> 0 | F7: =DATE($B$2,3,1) -> 46082 | G7: =EOMONTH(F7,0) -> 46112
A8: Abril | B8: =SUMIFS(Ingresos!$G:$G,Ingresos!$A:$A,">="&F8,Ingresos!$A:$A,"<="&G8) -> 0 | C8: =SUMIFS(Gastos!$F:$F,Gastos!$A:$A,">="&F8,Gastos!$A:$A,"<="&G8) -> 0 | D8: =B8-C8 -> 0 | F8: =DATE($B$2,4,1) -> 46113 | G8: =EOMONTH(F8,0) -> 46142
A9: Mayo | B9: =SUMIFS(Ingresos!$G:$G,Ingresos!$A:$A,">="&F9,Ingresos!$A:$A,"<="&G9) -> 0 | C9: =SUMIFS(Gastos!$F:$F,Gastos!$A:$A,">="&F9,Gastos!$A:$A,"<="&G9) -> 0 | D9: =B9-C9 -> 0 | F9: =DATE($B$2,5,1) -> 46143 | G9: =EOMONTH(F9,0) -> 46173
A10: Junio | B10: =SUMIFS(Ingresos!$G:$G,Ingresos!$A:$A,">="&F10,Ingresos!$A:$A,"<="&G10) -> 0 | C10: =SUMIFS(Gastos!$F:$F,Gastos!$A:$A,">="&F10,Gastos!$A:$A,"<="&G10) -> 0 | D10: =B10-C10 -> 0 | F10: =DATE($B$2,6,1) -> 46174 | G10: =EOMONTH(F10,0) -> 46203
A11: Julio | B11: =SUMIFS(Ingresos!$G:$G,Ingresos!$A:$A,">="&F11,Ingresos!$A:$A,"<="&G11) -> 0 | C11: =SUMIFS(Gastos!$F:$F,Gastos!$A:$A,">="&F11,Gastos!$A:$A,"<="&G11) -> 0 | D11: =B11-C11 -> 0 | F11: =DATE($B$2,7,1) -> 46204 | G11: =EOMONTH(F11,0) -> 46234
A12: Agosto | B12: =SUMIFS(Ingresos!$G:$G,Ingresos!$A:$A,">="&F12,Ingresos!$A:$A,"<="&G12) -> 0 | C12: =SUMIFS(Gastos!$F:$F,Gastos!$A:$A,">="&F12,Gastos!$A:$A,"<="&G12) -> 0 | D12: =B12-C12 -> 0 | F12: =DATE($B$2,8,1) -> 46235 | G12: =EOMONTH(F12,0) -> 46265
A13: Septiembre | B13: =SUMIFS(Ingresos!$G:$G,Ingresos!$A:$A,">="&F13,Ingresos!$A:$A,"<="&G13) -> 0 | C13: =SUMIFS(Gastos!$F:$F,Gastos!$A:$A,">="&F13,Gastos!$A:$A,"<="&G13) -> 0 | D13: =B13-C13 -> 0 | F13: =DATE($B$2,9,1) -> 46266 | G13: =EOMONTH(F13,0) -> 46295
A14: Octubre | B14: =SUMIFS(Ingresos!$G:$G,Ingresos!$A:$A,">="&F14,Ingresos!$A:$A,"<="&G14) -> 0 | C14: =SUMIFS(Gastos!$F:$F,Gastos!$A:$A,">="&F14,Gastos!$A:$A,"<="&G14) -> 0 | D14: =B14-C14 -> 0 | F14: =DATE($B$2,10,1) -> 46296 | G14: =EOMONTH(F14,0) -> 46326
A15: Noviembre | B15: =SUMIFS(Ingresos!$G:$G,Ingresos!$A:$A,">="&F15,Ingresos!$A:$A,"<="&G15) -> 0 | C15: =SUMIFS(Gastos!$F:$F,Gastos!$A:$A,">="&F15,Gastos!$A:$A,"<="&G15) -> 0 | D15: =B15-C15 -> 0 | F15: =DATE($B$2,11,1) -> 46327 | G15: =EOMONTH(F15,0) -> 46356
A16: Diciembre | B16: =SUMIFS(Ingresos!$G:$G,Ingresos!$A:$A,">="&F16,Ingresos!$A:$A,"<="&G16) -> 0 | C16: =SUMIFS(Gastos!$F:$F,Gastos!$A:$A,">="&F16,Gastos!$A:$A,"<="&G16) -> 0 | D16: =B16-C16 -> 0 | F16: =DATE($B$2,12,1) -> 46357 | G16: =EOMONTH(F16,0) -> 46387
A17: TOTAL | B17: =SUM(B5:B16) -> 0 | C17: =SUM(C5:C16) -> 0 | D17: =SUM(D5:D16) -> 0

Sheet IVU Mensual
A1: Planilla Mensual de IVU — Hoja de Trabajo (Formulario SC 2915)
A2: Radica en SURI antes del día 20 del mes siguiente. Esta hoja resume tus ventas y compras del mes para ayudarte a completar la planilla; el número final debe verificarse en SURI.
A4: Año: | B4: 2026
A6: Mes | B6: Ventas Sujetas a IVU | C6: Ventas Exentas | D6: IVU Cobrado (Ventas) | E6: IVU Pagado en Compras (Crédito) | F6: IVU Neto a Remitir | H6: Inicio | I6: Fin
A7: Enero | B7: =SUMIFS(Ingresos!$G:$G,Ingresos!$F:$F,"Sí",Ingresos!$A:$A,">="&H7,Ingresos!$A:$A,"<="&I7) -> 0 | C7: =SUMIFS(Ingresos!$G:$G,Ingresos!$F:$F,"No",Ingresos!$A:$A,">="&H7,Ingresos!$A:$A,"<="&I7) -> 0 | D7: =SUMIFS(Ingresos!$H:$H,Ingresos!$A:$A,">="&H7,Ingresos!$A:$A,"<="&I7) -> 0 | E7: =SUMIFS(Gastos!$H:$H,Gastos!$A:$A,">="&H7,Gastos!$A:$A,"<="&I7) -> 0 | F7: =D7-E7 -> 0 | H7: =DATE($B$4,1,1) -> 46023 | I7: =EOMONTH(H7,0) -> 46053
A8: Febrero | B8: =SUMIFS(Ingresos!$G:$G,Ingresos!$F:$F,"Sí",Ingresos!$A:$A,">="&H8,Ingresos!$A:$A,"<="&I8) -> 0 | C8: =SUMIFS(Ingresos!$G:$G,Ingresos!$F:$F,"No",Ingresos!$A:$A,">="&H8,Ingresos!$A:$A,"<="&I8) -> 0 | D8: =SUMIFS(Ingresos!$H:$H,Ingresos!$A:$A,">="&H8,Ingresos!$A:$A,"<="&I8) -> 0 | E8: =SUMIFS(Gastos!$H:$H,Gastos!$A:$A,">="&H8,Gastos!$A:$A,"<="&I8) -> 0 | F8: =D8-E8 -> 0 | H8: =DATE($B$4,2,1) -> 46054 | I8: =EOMONTH(H8,0) -> 46081
A9: Marzo | B9: =SUMIFS(Ingresos!$G:$G,Ingresos!$F:$F,"Sí",Ingresos!$A:$A,">="&H9,Ingresos!$A:$A,"<="&I9) -> 0 | C9: =SUMIFS(Ingresos!$G:$G,Ingresos!$F:$F,"No",Ingresos!$A:$A,">="&H9,Ingresos!$A:$A,"<="&I9) -> 0 | D9: =SUMIFS(Ingresos!$H:$H,Ingresos!$A:$A,">="&H9,Ingresos!$A:$A,"<="&I9) -> 0 | E9: =SUMIFS(Gastos!$H:$H,Gastos!$A:$A,">="&H9,Gastos!$A:$A,"<="&I9) -> 0 | F9: =D9-E9 -> 0 | H9: =DATE($B$4,3,1) -> 46082 | I9: =EOMONTH(H9,0) -> 46112
A10: Abril | B10: =SUMIFS(Ingresos!$G:$G,Ingresos!$F:$F,"Sí",Ingresos!$A:$A,">="&H10,Ingresos!$A:$A,"<="&I10) -> 0 | C10: =SUMIFS(Ingresos!$G:$G,Ingresos!$F:$F,"No",Ingresos!$A:$A,">="&H10,Ingresos!$A:$A,"<="&I10) -> 0 | D10: =SUMIFS(Ingresos!$H:$H,Ingresos!$A:$A,">="&H10,Ingresos!$A:$A,"<="&I10) -> 0 | E10: =SUMIFS(Gastos!$H:$H,Gastos!$A:$A,">="&H10,Gastos!$A:$A,"<="&I10) -> 0 | F10: =D10-E10 -> 0 | H10: =DATE($B$4,4,1) -> 46113 | I10: =EOMONTH(H10,0) -> 46142
A11: Mayo | B11: =SUMIFS(Ingresos!$G:$G,Ingresos!$F:$F,"Sí",Ingresos!$A:$A,">="&H11,Ingresos!$A:$A,"<="&I11) -> 0 | C11: =SUMIFS(Ingresos!$G:$G,Ingresos!$F:$F,"No",Ingresos!$A:$A,">="&H11,Ingresos!$A:$A,"<="&I11) -> 0 | D11: =SUMIFS(Ingresos!$H:$H,Ingresos!$A:$A,">="&H11,Ingresos!$A:$A,"<="&I11) -> 0 | E11: =SUMIFS(Gastos!$H:$H,Gastos!$A:$A,">="&H11,Gastos!$A:$A,"<="&I11) -> 0 | F11: =D11-E11 -> 0 | H11: =DATE($B$4,5,1) -> 46143 | I11: =EOMONTH(H11,0) -> 46173
A12: Junio | B12: =SUMIFS(Ingresos!$G:$G,Ingresos!$F:$F,"Sí",Ingresos!$A:$A,">="&H12,Ingresos!$A:$A,"<="&I12) -> 0 | C12: =SUMIFS(Ingresos!$G:$G,Ingresos!$F:$F,"No",Ingresos!$A:$A,">="&H12,Ingresos!$A:$A,"<="&I12) -> 0 | D12: =SUMIFS(Ingresos!$H:$H,Ingresos!$A:$A,">="&H12,Ingresos!$A:$A,"<="&I12) -> 0 | E12: =SUMIFS(Gastos!$H:$H,Gastos!$A:$A,">="&H12,Gastos!$A:$A,"<="&I12) -> 0 | F12: =D12-E12 -> 0 | H12: =DATE($B$4,6,1) -> 46174 | I12: =EOMONTH(H12,0) -> 46203
A13: Julio | B13: =SUMIFS(Ingresos!$G:$G,Ingresos!$F:$F,"Sí",Ingresos!$A:$A,">="&H13,Ingresos!$A:$A,"<="&I13) -> 0 | C13: =SUMIFS(Ingresos!$G:$G,Ingresos!$F:$F,"No",Ingresos!$A:$A,">="&H13,Ingresos!$A:$A,"<="&I13) -> 0 | D13: =SUMIFS(Ingresos!$H:$H,Ingresos!$A:$A,">="&H13,Ingresos!$A:$A,"<="&I13) -> 0 | E13: =SUMIFS(Gastos!$H:$H,Gastos!$A:$A,">="&H13,Gastos!$A:$A,"<="&I13) -> 0 | F13: =D13-E13 -> 0 | H13: =DATE($B$4,7,1) -> 46204 | I13: =EOMONTH(H13,0) -> 46234
A14: Agosto | B14: =SUMIFS(Ingresos!$G:$G,Ingresos!$F:$F,"Sí",Ingresos!$A:$A,">="&H14,Ingresos!$A:$A,"<="&I14) -> 0 | C14: =SUMIFS(Ingresos!$G:$G,Ingresos!$F:$F,"No",Ingresos!$A:$A,">="&H14,Ingresos!$A:$A,"<="&I14) -> 0 | D14: =SUMIFS(Ingresos!$H:$H,Ingresos!$A:$A,">="&H14,Ingresos!$A:$A,"<="&I14) -> 0 | E14: =SUMIFS(Gastos!$H:$H,Gastos!$A:$A,">="&H14,Gastos!$A:$A,"<="&I14) -> 0 | F14: =D14-E14 -> 0 | H14: =DATE($B$4,8,1) -> 46235 | I14: =EOMONTH(H14,0) -> 46265
A15: Septiembre | B15: =SUMIFS(Ingresos!$G:$G,Ingresos!$F:$F,"Sí",Ingresos!$A:$A,">="&H15,Ingresos!$A:$A,"<="&I15) -> 0 | C15: =SUMIFS(Ingresos!$G:$G,Ingresos!$F:$F,"No",Ingresos!$A:$A,">="&H15,Ingresos!$A:$A,"<="&I15) -> 0 | D15: =SUMIFS(Ingresos!$H:$H,Ingresos!$A:$A,">="&H15,Ingresos!$A:$A,"<="&I15) -> 0 | E15: =SUMIFS(Gastos!$H:$H,Gastos!$A:$A,">="&H15,Gastos!$A:$A,"<="&I15) -> 0 | F15: =D15-E15 -> 0 | H15: =DATE($B$4,9,1) -> 46266 | I15: =EOMONTH(H15,0) -> 46295
A16: Octubre | B16: =SUMIFS(Ingresos!$G:$G,Ingresos!$F:$F,"Sí",Ingresos!$A:$A,">="&H16,Ingresos!$A:$A,"<="&I16) -> 0 | C16: =SUMIFS(Ingresos!$G:$G,Ingresos!$F:$F,"No",Ingresos!$A:$A,">="&H16,Ingresos!$A:$A,"<="&I16) -> 0 | D16: =SUMIFS(Ingresos!$H:$H,Ingresos!$A:$A,">="&H16,Ingresos!$A:$A,"<="&I16) -> 0 | E16: =SUMIFS(Gastos!$H:$H,Gastos!$A:$A,">="&H16,Gastos!$A:$A,"<="&I16) -> 0 | F16: =D16-E16 -> 0 | H16: =DATE($B$4,10,1) -> 46296 | I16: =EOMONTH(H16,0) -> 46326
A17: Noviembre | B17: =SUMIFS(Ingresos!$G:$G,Ingresos!$F:$F,"Sí",Ingresos!$A:$A,">="&H17,Ingresos!$A:$A,"<="&I17) -> 0 | C17: =SUMIFS(Ingresos!$G:$G,Ingresos!$F:$F,"No",Ingresos!$A:$A,">="&H17,Ingresos!$A:$A,"<="&I17) -> 0 | D17: =SUMIFS(Ingresos!$H:$H,Ingresos!$A:$A,">="&H17,Ingresos!$A:$A,"<="&I17) -> 0 | E17: =SUMIFS(Gastos!$H:$H,Gastos!$A:$A,">="&H17,Gastos!$A:$A,"<="&I17) -> 0 | F17: =D17-E17 -> 0 | H17: =DATE($B$4,11,1) -> 46327 | I17: =EOMONTH(H17,0) -> 46356
A18: Diciembre | B18: =SUMIFS(Ingresos!$G:$G,Ingresos!$F:$F,"Sí",Ingresos!$A:$A,">="&H18,Ingresos!$A:$A,"<="&I18) -> 0 | C18: =SUMIFS(Ingresos!$G:$G,Ingresos!$F:$F,"No",Ingresos!$A:$A,">="&H18,Ingresos!$A:$A,"<="&I18) -> 0 | D18: =SUMIFS(Ingresos!$H:$H,Ingresos!$A:$A,">="&H18,Ingresos!$A:$A,"<="&I18) -> 0 | E18: =SUMIFS(Gastos!$H:$H,Gastos!$A:$A,">="&H18,Gastos!$A:$A,"<="&I18) -> 0 | F18: =D18-E18 -> 0 | H18: =DATE($B$4,12,1) -> 46357 | I18: =EOMONTH(H18,0) -> 46387
A19: TOTAL | B19: =SUM(B7:B18) -> 0 | C19: =SUM(C7:C18) -> 0 | D19: =SUM(D7:D18) -> 0 | E19: =SUM(E7:E18) -> 0 | F19: =SUM(F7:F18) -> 0
A21: Nota: la tasa combinada de IVU en Puerto Rico es 10.5% estatal + 1% municipal = 11.5% en la mayoría de los artículos tangibles. Algunos servicios y productos tienen tasas distintas (ej. alimentos preparados 7%, servicios B2B 4%). Confirma la tasa correcta por transacción al registrar tus ventas en la pestaña Ingresos.

Sheet Contribución sobre Ingresos
A1: Resumen Anual — Contribución sobre Ingresos
A2: Año: | B2: 2026
A4: Ingresos
A5: Ingresos Totales del Negocio | B5: =SUMIFS(Ingresos!$G:$G,Ingresos!$A:$A,">="&DATE($B$2,1,1),Ingresos!$A:$A,"<="&DATE($B$2,12,31)) -> 0
A7: Gastos por Categoría
A8: Categoría | B8: Monto
A9: Materiales y Suministros | B9: =SUMIFS(Gastos!$F:$F,Gastos!$D:$D,"Materiales y Suministros",Gastos!$A:$A,">="&DATE($B$2,1,1),Gastos!$A:$A,"<="&DATE($B$2,12,31)) -> 0
A10: Herramientas y Equipo | B10: =SUMIFS(Gastos!$F:$F,Gastos!$D:$D,"Herramientas y Equipo",Gastos!$A:$A,">="&DATE($B$2,1,1),Gastos!$A:$A,"<="&DATE($B$2,12,31)) -> 0
A11: Mercadeo y Publicidad | B11: =SUMIFS(Gastos!$F:$F,Gastos!$D:$D,"Mercadeo y Publicidad",Gastos!$A:$A,">="&DATE($B$2,1,1),Gastos!$A:$A,"<="&DATE($B$2,12,31)) -> 0
A12: Transporte y Millaje | B12: =SUMIFS(Gastos!$F:$F,Gastos!$D:$D,"Transporte y Millaje",Gastos!$A:$A,">="&DATE($B$2,1,1),Gastos!$A:$A,"<="&DATE($B$2,12,31)) -> 0
A13: Servicios Profesionales (contable/legal) | B13: =SUMIFS(Gastos!$F:$F,Gastos!$D:$D,"Servicios Profesionales (contable/legal)",Gastos!$A:$A,">="&DATE($B$2,1,1),Gastos!$A:$A,"<="&DATE($B$2,12,31)) -> 0
A14: Renta y Utilidades | B14: =SUMIFS(Gastos!$F:$F,Gastos!$D:$D,"Renta y Utilidades",Gastos!$A:$A,">="&DATE($B$2,1,1),Gastos!$A:$A,"<="&DATE($B$2,12,31)) -> 0
A15: Empaque y Envío | B15: =SUMIFS(Gastos!$F:$F,Gastos!$D:$D,"Empaque y Envío",Gastos!$A:$A,">="&DATE($B$2,1,1),Gastos!$A:$A,"<="&DATE($B$2,12,31)) -> 0
A16: Comisiones de Plataforma (Shopify/Etsy/pasarela de pago) | B16: =SUMIFS(Gastos!$F:$F,Gastos!$D:$D,"Comisiones de Plataforma (Shopify/Etsy/pasarela de pago)",Gastos!$A:$A,">="&DATE($B$2,1,1),Gastos!$A:$A,"<="&DATE($B$2,12,31)) -> 0
A17: Seguros | B17: =SUMIFS(Gastos!$F:$F,Gastos!$D:$D,"Seguros",Gastos!$A:$A,">="&DATE($B$2,1,1),Gastos!$A:$A,"<="&DATE($B$2,12,31)) -> 0
A18: Misceláneos | B18: =SUMIFS(Gastos!$F:$F,Gastos!$D:$D,"Misceláneos",Gastos!$A:$A,">="&DATE($B$2,1,1),Gastos!$A:$A,"<="&DATE($B$2,12,31)) -> 0
A19: Total Gastos | B19: =SUM(B9:B18) -> 0
A21: Utilidad Neta antes de Contribuciones | B21: =B5-B19 -> 0
A23: ¿Qué planilla corresponde? Depende de cómo esté clasificada Evergreen Love L.L.C. ante Hacienda: • Si no se hizo elección especial, Hacienda trata la LLC como CORPORACIÓN → Formulario 480.20 (Planilla de Contribución sobre Ingresos de Corporaciones). • Si se eligió tributar como SOCIEDAD (partnership) bajo la Sección 1010.05 → Formulario 480.10(SE)/480.6 y cada socio reporta su participación distributiva. • Si se eligió ENTIDAD NO TOMADA EN CUENTA (disregarded entity, un solo dueño) → los ingresos y gastos de este resumen se reportan en la Planilla Individual (Formulario 482) de Myriam, usualmente en el Anejo de negocio propio. Confirma la clasificación de la LLC con tu CPA antes de radicar — este resumen te da los números, no la forma legal de reportarlos.

Sheet Guía y Fechas
A1: Guía Rápida — Planillas de Evergreen Love L.L.C.
A3: Planilla | B3: Detalle
A4: IVU Mensual (Formulario SC 2915) | B4: Se radica en línea a través de SURI (Sistema Unificado de Rentas Internas). Fecha límite: día 20 de cada mes, reportando las ventas del mes anterior. Usa la pestaña 'IVU Mensual' de este libro como hoja de trabajo.
A5: Tasa de IVU en Puerto Rico | B5: 10.5% estatal + 1% municipal = 11.5% combinado en la mayoría de los bienes tangibles vendidos en Guaynabo. Algunos servicios/artículos tienen tasas especiales (ej. alimentos preparados 7%, servicios B2B 4%, artículos exentos 0%). Verifica la tasa aplicable a cada producto/servicio antes de cobrar.
A6: Contribución sobre Ingresos | B6: Planilla anual ante el Departamento de Hacienda. El formulario correcto (480.20 Corporación, 480.10/480.6 Sociedad, o Individual 482 si es entidad no tomada en cuenta) depende de la clasificación contributiva elegida para la LLC. Usualmente vence el 15 de abril siguiente al año contributivo, con posibilidad de prórroga automática. Verifica la fecha exacta y el formulario en hacienda.pr.gov o con tu CPA, ya que puede variar según la clasificación y si se radicó prórroga.
A7: Registro de Comerciante / Patente Municipal | B7: Verifica anualmente con el Municipio de Guaynabo si aplica la Declaración de Volumen de Negocios para la Patente Municipal (usualmente antes del 15 de abril).
A8: Recordatorio | B8: Este libro organiza tus números pero no sustituye a un CPA. Antes de radicar cualquier planilla, confirma cifras, clasificación de la entidad y deducciones permitidas con un profesional de contabilidad en Puerto Rico.
